mantarray_magnet_finding/__init__.py
mantarray_magnet_finding/constants.py
mantarray_magnet_finding/exceptions.py
mantarray_magnet_finding/magnet_finding.py
mantarray_magnet_finding/utils.py
pulse3D/__init__.py
pulse3D/compression_cy.cp39-win_amd64.pyd
pulse3D/compression_cy.pyx
pulse3D/constants.py
pulse3D/excel_writer.py
pulse3D/exceptions.py
pulse3D/magnet_finding.py
pulse3D/metrics.py
pulse3D/nb_peak_detection.py
pulse3D/peak_detection.py
pulse3D/plate_recording.py
pulse3D/plotting.py
pulse3D/stimulation.py
pulse3D/transforms.py
pulse3D/utils.py
Pulse3D-0.34.5.dist-info/LICENSE
Pulse3D-0.34.5.dist-info/METADATA
Pulse3D-0.34.5.dist-info/WHEEL
Pulse3D-0.34.5.dist-info/top_level.txt
Pulse3D-0.34.5.dist-info/RECORD
