Metadata-Version: 2.1
Name: Pulse3D
Version: 0.34.5
Summary: Pulse3D Analysis Platform
Home-page: https://github.com/CuriBio/Pulse3D
Author: Curi Bio
Author-email: contact@curibio.com
License: MIT
Project-URL: Documentation, https://pulse3D.readthedocs.io/en/latest/
Platform: UNKNOWN
Classifier: Development Status :: 1 - Planning
Classifier: Intended Audience :: Science/Research
Classifier: License :: OSI Approved :: MIT License
Classifier: Programming Language :: Python
Classifier: Programming Language :: Python :: 3
Classifier: Programming Language :: Python :: 3.9
Classifier: Programming Language :: Python :: 3.10
Classifier: Programming Language :: Python :: 3.11
Classifier: Topic :: Scientific/Engineering
License-File: LICENSE
Requires-Dist: h5py >=3.8.0
Requires-Dist: nptyping ==1.4.4
Requires-Dist: numpy >=1.23.4
Requires-Dist: scipy ==1.9.3
Requires-Dist: numba ==0.57.0
Requires-Dist: immutabledict >=1.2.0
Requires-Dist: XlsxWriter >=1.3.8
Requires-Dist: openpyxl >=3.0.7
Requires-Dist: stdlib-utils >=0.4.4
Requires-Dist: labware-domain-models >=0.3.1
Requires-Dist: semver >=2.13.0
Requires-Dist: pandas ==1.5.3
Requires-Dist: pyarrow ==12.0.0
Requires-Dist: structlog ==23.2.0
Requires-Dist: importlib-metadata >=3.7.3 ; python_version < "3.8"
